otp_mcp/__init__.py
otp_mcp/__main__.py
otp_mcp/common.py
otp_mcp/resource.py
otp_mcp/server.py
otp_mcp/tool.py
otp_mcp_server-0.3.0.dist-info/licenses/LICENSE
otp_mcp_server-0.3.0.dist-info/METADATA
otp_mcp_server-0.3.0.dist-info/WHEEL
otp_mcp_server-0.3.0.dist-info/entry_points.txt
otp_mcp_server-0.3.0.dist-info/top_level.txt
otp_mcp_server-0.3.0.dist-info/RECORD
