Metadata-Version: 2.4
Name: otp-mcp-server
Version: 0.3.0
Summary: MCP Server for OTP
Author-email: Andrea Bonomi <andrea.bonomi@example.com>
License-Expression: MIT
Project-URL: GitHub, https://github.com/andreax79/otp-mcp
Project-URL: Issues, https://github.com/andreax79/otp-mcp/issues
Keywords: otp,mcp,totp,web-automation,ai-tools,mcp-server
Classifier: Programming Language :: Python :: 3
Classifier: Operating System :: OS Independent
Requires-Python: >=3.11
License-File: LICENSE
Requires-Dist: click
Requires-Dist: fastmcp
Requires-Dist: freakotp
Requires-Dist: securid
Provides-Extra: dev
Requires-Dist: black; extra == "dev"
Requires-Dist: isort; extra == "dev"
Requires-Dist: pytest; extra == "dev"
Requires-Dist: pytest-asyncio; extra == "dev"
Requires-Dist: pytest-cov; extra == "dev"
Dynamic: license-file
